Workbook

Sheet Recursos Humanos
A1: Costos de Recursos Humanos (Salario Actual)
A2: Recurso Humano | B2: Salario Mensual Estimado (COP) | C2: Salario Diario Aprox. (COP) | D2: Salario Hora
A3: Líder de Proyecto | B3: 2938675 | C3: =B3/30 -> 97955.833 | D3: =C3/8 -> 12244.479
A4: Diseñador Software (UI/UX) | B4: 3500000 | C4: =B4/30 -> 116666.67 | D4: =C4/8 -> 14583.333
A5: Desarrollador Backend | B5: 3000000 | C5: =B5/30 -> 100000 | D5: =C5/8 -> 12500
A6: Analista de Software | B6: 3000000 | C6: =B6/30 -> 100000 | D6: =C6/8 -> 12500
A7: Documentador Técnico | B7: 3500000 | C7: =B7/30 -> 116666.67 | D7: =C7/8 -> 14583.333
A8: Administrador de BBDD | B8: 4000000 | C8: =B8/30 -> 133333.33 | D8: =C8/8 -> 16666.667
A9: Ingeniero de Pruebas | B9: 3000000 | C9: =B9/30 -> 100000 | D9: =C9/8 -> 12500
A10: Desarrollador Fronted | B10: 3000000 | C10: =B10/30 -> 100000 | D10: =C10/8 -> 12500
A11: Arquitecto de Software | B11: 4530433 | C11: =B11/30 -> 151014.43 | D11: =C11/8 -> 18876.804
A12: Costo Total | B12: =SUM(B3:B11) -> 30469108 | C12: =SUM(C3:C11) -> 1015636.9 | D12: =SUM(D3:D11) -> 126954.62

Sheet Desarrollo Actual
A1: Costos de Desarrollo (Hasta el Momento)
A2: Actividad | B2: Estimación en Días | C2: Horas Trabajadas x Día | D2: Trabajo en Horas Estimadas | E2: Costo por Día (COP) | F2: Costo por Hora (COP) | G2: Costo Estimado (COP)
A3: BPMN (Modelado de Procesos de Negocio) | B3: 2 | C3: 4 | D3: =B3*C3 -> 8 | E3: =F3*C3 -> 50000 | F3: 12500 | G3: =E3*B3 -> 100000
A4: Desarrollo Casos de Uso (Diagrama) | B4: 8 | C4: 8 | D4: =B4*C4 -> 64 | E4: =F4*C4 -> 100000 | F4: 12500 | G4: =E4*B4 -> 800000
A5: Desarrollo Casos de Uso Extendido(Documentación) | B5: 5 | C5: 8 | D5: =B5*C5 -> 40 | E5: =F5*C5 -> 100000 | F5: 12500 | G5: =E5*B5 -> 500000
A6: Desarrollo Mockups | B6: 5 | C6: 8 | D6: =B6*C6 -> 40 | E6: =F6*C6 -> 100000 | F6: 12500 | G6: =E6*B6 -> 500000
A7: Desarrollo Modelo de Entidad-Relación (MER) | B7: 4 | C7: 8 | D7: =B7*C7 -> 32 | E7: =F7*C7 -> 133333.33 | F7: 16666.667 | G7: =E7*B7 -> 533333.33
A8: Costo Total | B8: =SUM(B3:B7) -> 24 | D8: =SUM(D3:D7) -> 184 | E8: =SUM(E3:E7) -> 483333.33 | F8: =SUM(F3:F7) -> 66666.667 | G8: =G3+G4+G5+G6+G7 -> 2433333.3

Sheet Soporte y Mantenimiento
A1: Costos de Soporte y Mantenimiento (Semestral)
A2: Actividad | B2: Incluye | C2: Estimación Plan Mensual (COP) | D2: Estimación Plan Semestral (COP) | E2: Con Descuento de 10% si es Plan Semestral
A3: Soporte Técnico | B3: Atención y correción de fallas Backups del sistema Acompañamiento remoto SLA (Acuerdo de Nivel de Servicio) Asistencia en configuración o ajustes menores | C3: 500000 | D3: =C3*6 -> 3000000 | E3: =D3-(D3*0.1) -> 2700000
A4: Actualizaciones del Sistema | B4: Aplicación de parches Actualización de servicios Corrección de vulnerabilidades de seguridad Revisión y optimización de bases de datos | C4: 300000 | D4: =C4*6 -> 1800000 | E4: =D4-(D4*0.1) -> 1620000
A5: Monitoreo del Sistema | B5: Monitoreo de base de datos Revisión de errores en tiempo real o programados Monitoreo de Seguridad | C5: 300000 | D5: =C5*6 -> 1800000 | E5: =D5-(D5*0.1) -> 1620000
A6: Costo Total | C6: =SUM(C2:C5) -> 1100000 | D6: =SUM(D2:D5) -> 6600000 | E6: =SUM(E2:E5) -> 5940000

Sheet Administración y Documentación
A1: Costos Administrativos y de Documentación
A2: Recurso | B2: Costo Estimado (COP)
A3: Documentación del sistema | B3: 1750000
A4: Manual de usuario | B4: 1500000
A5: Costo Total | B5: =B3+B4 -> 3250000

Sheet Recursos Humano (Día)
A1: Costos de Recursos Humanos (Por Día)
A2: Recurso Humano | B2: Salario Diario Aprox. (COP) | C2: Fuente para Justificar Salario
A3: Líder de Proyecto | B3: =VLOOKUP('Recursos Humano (Día)'!A3,'Recursos Humanos'!A3:D11,3,FALSE) -> 97955.833 | C3: https://co.indeed.com/career/l%C3%ADder-de-proyectos/salaries?utm_source=chatgpt.com
A4: Diseñador Software (UI/UX) | B4: =VLOOKUP('Recursos Humano (Día)'!A4,'Recursos Humanos'!A4:D12,3,FALSE) -> 116666.67 | C4: https://image.email.page.com/lib/fe3711717564047b761d70/m/1/3b1b65df-f6f3-4ed3-8d44-fc82a34446d1.pdf?utm_source=chatgpt.com
A5: Desarrollador Backend | B5: =VLOOKUP('Recursos Humano (Día)'!A5,'Recursos Humanos'!A5:D13,3,FALSE) -> 100000 | C5: https://image.email.page.com/lib/fe3711717564047b761d70/m/1/3b1b65df-f6f3-4ed3-8d44-fc82a34446d1.pdf?utm_source=chatgpt.com
A6: Analista de Software | B6: =VLOOKUP('Recursos Humano (Día)'!A6,'Recursos Humanos'!A6:D14,3,FALSE) -> 100000 | C6: https://image.email.page.com/lib/fe3711717564047b761d70/m/1/3b1b65df-f6f3-4ed3-8d44-fc82a34446d1.pdf?utm_source=chatgpt.com
A7: Documentador Técnico | B7: =VLOOKUP('Recursos Humano (Día)'!A7,'Recursos Humanos'!A7:D15,3,FALSE) -> 116666.67 | C7: https://www.glassdoor.com.mx/Sueldos/colombia-technical-writer-sueldo-SRCH_IL.0%2C8_IN54_KO9%2C25.htm?utm_source=chatgpt.com
A8: Administrador de BBDD | B8: =VLOOKUP('Recursos Humano (Día)'!A8,'Recursos Humanos'!A8:D16,3,FALSE) -> 133333.33 | C8: https://image.email.page.com/lib/fe3711717564047b761d70/m/1/3b1b65df-f6f3-4ed3-8d44-fc82a34446d1.pdf?utm_source=chatgpt.com
A9: Ingeniero de Pruebas | B9: =VLOOKUP('Recursos Humano (Día)'!A9,'Recursos Humanos'!A9:D17,3,FALSE) -> 100000 | C9: https://image.email.page.com/lib/fe3711717564047b761d70/m/1/3b1b65df-f6f3-4ed3-8d44-fc82a34446d1.pdf?utm_source=chatgpt.com
A10: Desarrollador Fronted | B10: =VLOOKUP('Recursos Humano (Día)'!A10,'Recursos Humanos'!A10:D18,3,FALSE) -> 100000 | C10: https://image.email.page.com/lib/fe3711717564047b761d70/m/1/3b1b65df-f6f3-4ed3-8d44-fc82a34446d1.pdf?utm_source=chatgpt.com
A11: Arquitecto de Software | B11: =VLOOKUP('Recursos Humano (Día)'!A11,'Recursos Humanos'!A11:D19,3,FALSE) -> 151014.43 | C11: https://www.magneto365.com/co/cargos/informatica-tecnologia-sistemas/arquitecto-software?utm_source=chatgpt.com
A12: Costo Total | B12: =VLOOKUP('Recursos Humano (Día)'!A12,'Recursos Humanos'!A12:D20,3,FALSE) -> 1015636.9

Sheet Servidores Físicos
A1: Costos de Servidor Físico - 1era Opción | I1: Costos de Servidor Físico - 2nda Opción
A2: Producto / Servicio | B2: Muestra Visual | C2: Descripción | D2: Cantidad | E2: Valor Unitario Cotizado (COP) | F2: Subtotal (COP) | I2: Producto / Servicio | J2: Muestra Visual | K2: Descripción | L2: Cantidad | M2: Valor Unitario Cotizado (COP) | N2: Subtotal (COP)
A3: Servidor Lenovo ThinkSystem ST45 V3 con AMD EPYC 4124P | C3: Cuenta con un potente procesador AMD EPYC 4124P de 4 núcleos, 16 GB de RAM y un disco duro de 2 TB. Ideal para pequeñas y medianas empresas que requieren rendimiento y fiabilidad en sus operaciones | D3: 1 | E3: 3957245 | F3: =E3*'Servidores Físicos'!$D3 -> 3957245 | I3: Servidor Dell PowerEdge T160 | K3: Servidor de torre robusto, diseñado para ofrecer un alto rendimiento con capacidad para hasta 3 discos duros de 3.5 pulgadas. Equipado con un procesador Intel Xeon Performance 6315P de 6 núcleos, 16GB de memoria DDR5 ECC, y una gestión avanzada con iDRAC9 Basic 15G | L3: 1 | M3: 5013551 | N3: =M3*'Servidores Físicos'!$L3 -> 5013551
A4: Gabinete Rack De Piso 24ru 120x60x60 | C4: Armario o estructura metálica diseñada para alojar y montar servidores, ups y unidades de almacenamiento de manera organizada, segura y estandarizada. | D4: 1 | E4: 549206 | F4: =E4*'Servidores Físicos'!$D4 -> 549206 | I4: Gabinete Rack De Piso 24ru 120x60x60 | K4: Armario o estructura metálica diseñada para alojar y montar servidores, ups y unidades de almacenamiento de manera organizada, segura y estandarizada. | L4: 1 | M4: 549206 | N4: =M4*'Servidores Físicos'!$L4 -> 549206
A5: (PSU) Fuente de poder Lenovo Thinksystem 550w Platinium 7n67a00882 | C5: Dispositivo que suministra energía eléctrica a todos los componentes del equipo. Crucial para el correcto funcionamiento en servidores y racks | D5: 1 | E5: 939900 | F5: =E5*'Servidores Físicos'!$D5 -> 939900 | I5: (PSU) Unidad de fuente de alimentación original Dell 750 W servidor Poweredge | K5: Dispositivo que suministra energía eléctrica a todos los componentes del equipo. Crucial para el correcto funcionamiento en servidores y racks | L5: 1 | M5: 595957 | N5: =M5*'Servidores Físicos'!$L5 -> 595957
A6: (UPS) APC - BR1500MS2 - Backup UPS Pro 1500 VA Line Interactive Tower - 10 tomas de corriente | C6: Sistema de Alimentación Ininterrumpida que suministra energía eléctrica a equipos electrónicos cuando falla la corriente eléctrica | D6: 1 | E6: 1303553 | F6: =E6*'Servidores Físicos'!$D6 -> 1303553 | I6: (UPS) Apc Pro 1500va 2p Usb Avr 900w 120v Br1500m2-lm Negro | K6: Sistema de Alimentación Ininterrumpida que suministra energía eléctrica a equipos electrónicos cuando falla la corriente eléctrica | L6: 1 | M6: 1473800 | N6: =M6*'Servidores Físicos'!$L6 -> 1473800
A7: Instalación físca en sala de servidores (espacio + cableado + UPS + server + PSU) | C7: Proceso de poner en funcionamiento físico y lógico un servidor dentro de un rack o sala de servidores, asegurando que todo el hardware y software funcione correctamente | D7: 1 | E7: 1000000 | F7: =E7*'Servidores Físicos'!$D7 -> 1000000 | I7: Instalación físca en sala de servidores (espacio + cableado + UPS + server + PSU) | K7: Proceso de poner en funcionamiento físico y lógico un servidor dentro de un rack o sala de servidores, asegurando que todo el hardware y software funcione correctamente | L7: 1 | M7: 1000000 | N7: =M7*'Servidores Físicos'!$L7 -> 1000000
A8: Windows server 2019 (Edición Standard) | C8: Software que gestiona los recursos de un servidor y permite que varios usuarios o dispositivos accedan a ellos de forma controlada y segura | D8: 1 | E8: 120000 | F8: =E8*'Servidores Físicos'!$D8 -> 120000 | I8: Windows server 2019 (Edición Standard) | K8: Software que gestiona los recursos de un servidor y permite que varios usuarios o dispositivos accedan a ellos de forma controlada y segura | L8: 1 | M8: 120000 | N8: =M8*'Servidores Físicos'!$L8 -> 120000
A9: Configuración inicial, backup y pruebas | C9: Es todo lo que se hace después de montar físicamente el servidor y conectarlo a la red y a la electricidad, para que funcione correctamente | D9: 1 | E9: 500000 | F9: =E9*'Servidores Físicos'!$D9 -> 500000 | I9: Configuración inicial, backup y pruebas | K9: Es todo lo que se hace después de montar físicamente el servidor y conectarlo a la red y a la electricidad, para que funcione correctamente | L9: 1 | M9: 500000 | N9: =M9*'Servidores Físicos'!$L9 -> 500000
A10: Costo Total | D10: =SUM('Servidores Físicos'!$D$3:$D$9) -> 7 | F10: =SUM(F3:F9) -> 8369904 | I10: Costo Total | L10: =SUM('Servidores Físicos'!$L$3:$L$9) -> 7 | N10: =SUM(N3:N9) -> 9252514

Sheet Servidores Web - Hosting
A1: Costos de Servidor Web - 1era Opción | F1: Costos de Servidor Web - 2nda Opción
A2: Concepto | B2: Detalle | C2: Valor Anual Cotizado (COP) | F2: Concepto | G2: Detalle | H2: Valor Anual Cotizado (COP)
A3: Hosting en Colombia (Plan H1) | B3: 10 GB Espacio SSD NVMe 500 GB de Tráfico / mes 2 CPU / Garantizado 4 GB de memoria RAM IPv4 + IPv6 activado 10 Cuentas E-mail 2 Bases de datos 1 Dominio permitido WordPress / Joomla / Otros LiteSpeed + LSCache Seguridad Imunify360 Constructor de sitios Pro Copias de seguridad | C3: 90000 | F3: Colombia Cloud (Plan Básico) Renovación: $139.900 | G3: Espacio de almacenamiento: 10 GB NVMe Ultra. Tráfico mensual permitido: 1 TB / mes. Memoria RAM: 4 GB DDR5. CPU: 2 vCPU, con procesador AMD Epyc. Cuentas de correo: 20 cuentas. Bases de datos: 8 bases de datos. Copias de seguridad: incluidas. Webserver: LiteSpeed + LSCache para acelerar la web. Seguridad: Incluye “Antihack Imunify360” y protección DDoS. Aplicaciones: Soporta WordPress, Joomla y más de 200 apps. Staging (entorno de prueba): incluido. No incluye acceso SSH en este plan. | H3: 89900
A4: Dominio incluido | B4: 1 Dominio Permitido (Viene con el plan) | C4: 0 | F4: Dominio incluido | G4: 1 Sitio Web Permitido (Viene con el plan) | H4: 0
A5: Certificado SSL | B5: Gratis con el plan (https://) | C5: 0 | F5: Certificado SSL | G5: Incluido en el plan | H5: 0
A6: Soporte técnico | B6: Incluido en el plan | C6: 0 | F6: Soporte técnico | G6: 24/7 en español | H6: 0
A7: Duración | B7: 12 Meses | C7: 0 | F7: Duración | G7: 12 Meses | H7: 0
A8: Costo Total | C8: =SUM(C3:C7) -> 90000 | F8: Costo Total | H8: =SUM(H3:H7) -> 89900

Sheet Equipo Desarrolladores
A1: Costos Equipo Desarrolladores
A2: Equipo | B2: Muestra Visual | C2: Procesador | D2: Especificaciones | E2: Cantidad | F2: Proveedores y Precios | I2: Recomendación
F3: Falabella | G3: Mercado Libre | H3: Éxito | I3: Precio | J3: Proveedor
A4: LENOVO 82YX003CLM | C4: AMD Ryzen™ 7 7730U | D4: Portátil SSD 1 TB de Almacenamiento 24 GB de Memoria RAM Anti Glare, FHD 1 Año de Garantía Conexión Ethernet, HDMI, USB, USB-C 1920x1080 de Resolución de Pantalla Tarjeta Gráfica Integrada | E4: 1 | F4: 2200000 | G4: 2490000 | H4: 2150000 | I4: =MIN(F4:H4) -> 2150000 | J4: =INDEX($F$3:$H$3, MATCH(I4, F4:H4, 0)) -> Éxito
A5: LENOVO THINKCENTRE NEO 50A 24 GEN 5 | C5: Intel® Core™ i7-13620H | D5: All in one SSD 1 TB de Almacenamiento 16 GB de Memoria RAM FHD, IPS 1 Año de Garantía Conexión Bluetooth, Ethernet, HDMI, USB, Wifi 1920x1080 de Resolución de Pantalla Tarjeta Gráfica Integrada | E5: 1 | F5: 2930000 | G5: 3309000 | H5: 3500000 | I5: =MIN(F5:H5) -> 2930000 | J5: =INDEX($F$3:$H$3, MATCH(I5, F5:H5, 0)) -> Falabella
A6: HP 15-FD0006LA | C6: Intel® Core™ I7-1355U | D6: Portátil SSD 1 TB de Almacenamiento 12 GB de Memoria RAM FHD 1 Año de Garantía Conexión Bluetooth, Wifi 1920x1080 de Resolución de Pantalla Tarjeta Gráfica Intel IRIS Xe GRAPHICS | E6: 1 | F6: 3110000 | G6: 3110000 | H6: 3449900 | I6: =MIN(F6:H6) -> 3110000 | J6: =INDEX($F$3:$H$3, MATCH(I6, F6:H6, 0)) -> Falabella

Sheet Equipos Consultorio
A1: Costos Equipos Consultorio
A2: Equipo | B2: Muestra Visual | C2: Procesador | D2: Especificaciones | E2: Cantidad | F2: Proveedores y Precios | I2: Recomendación
F3: Falabella | G3: Mercado Libre | H3: Éxito | I3: Precio | J3: Proveedor | K3: Subtotal
A4: LENOVO 82YX003CLM | C4: AMD Ryzen™ 7 7730U | D4: Portátil SSD 1 TB de Almacenamiento 24 GB de Memoria RAM Anti Glare, FHD 1 Año de Garantía Conexión Ethernet, HDMI, USB, USB-C 1920x1080 de Resolución de Pantalla Tarjeta Gráfica Integrada | E4: 2 | F4: 2200000 | G4: 2490000 | H4: 2150000 | I4: =MIN(F4:H4) -> 2150000 | J4: =INDEX($F$3:$H$3, MATCH(I4, F4:H4, 0)) -> Éxito | K4: =I4*E4 -> 4300000
A5: LENOVO THINKCENTRE NEO 50A 24 GEN 5 | C5: Intel® Core™ i7-13620H | D5: All in one SSD 1 TB de Almacenamiento 16 GB de Memoria RAM FHD, IPS 1 Año de Garantía Conexión Bluetooth, Ethernet, HDMI, USB, Wifi 1920x1080 de Resolución de Pantalla Tarjeta Gráfica Integrada | E5: 2 | F5: 2930000 | G5: 3309000 | H5: 3500000 | I5: =MIN(F5:H5) -> 2930000 | J5: =INDEX($F$3:$H$3, MATCH(I5, F5:H5, 0)) -> Falabella | K5: =I5*E5 -> 5860000
A6: HP 15-FD0006LA | C6: Intel® Core™ I7-1355U | D6: Portátil SSD 1 TB de Almacenamiento 12 GB de Memoria RAM FHD 1 Año de Garantía Conexión Bluetooth, Wifi 1920x1080 de Resolución de Pantalla Tarjeta Gráfica Intel IRIS Xe GRAPHICS | E6: 2 | F6: 3110000 | G6: 3110000 | H6: 3449900 | I6: =MIN(F6:H6) -> 3110000 | J6: =INDEX($F$3:$H$3, MATCH(I6, F6:H6, 0)) -> Falabella | K6: =I6*E6 -> 6220000

Sheet Cotización Total
A1: Primera Cotización | D1: Segunda Cotización | G1: Marco de Trabajo para el Desarrollo
A2: Categoría | B2: Valor Estimado (COP) | D2: Categoría | E2: Valor Estimado (COP) | G2: Metodología | H2: Descripción | I2: Elementos del Proceso | J2: Beneficios
A3: Recursos Humanos (Mensual) | B3: ='Recursos Humanos'!B12 -> 30469108 | D3: Recursos Humanos (Mensual) | E3: ='Recursos Humanos'!B12 -> 30469108 | G3: Scrum | H3: Para el desarrollo del software se utilizará la metodología Scrum, un marco ágil que permite gestionar el proyecto de forma iterativa e incremental, garantizando flexibilidad, transparencia y entregables continuos de valor | I3: Sprints: Ciclos de desarrollo (según acuerdo con el cliente). En donde se planifican, desarrollan y entregan funcionalidades completas y probadas | J3: Mayor capacidad de adaptación a cambios
A4: Desarrollo Actual | B4: ='Desarrollo Actual'!G8 -> 2433333.3 | D4: Desarrollo Actual | E4: ='Desarrollo Actual'!G8 -> 2433333.3
A5: Soporte y Mantenimiento (Semestral) | B5: ='Soporte y Mantenimiento'!E6 -> 5940000 | D5: Soporte y Mantenimiento (Semestral) | E5: ='Soporte y Mantenimiento'!E6 -> 5940000 | J5: Entregables frecuentes
A6: Administración y Documentación | B6: ='Administración y Documentación'!B5 -> 3250000 | D6: Administración y Documentación | E6: ='Administración y Documentación'!B5 -> 3250000 | I6: Product Backlog: Lista priorizada de requerimientos del proyecto
A7: Servidor Físico | B7: ='Servidores Físicos'!F10 -> 8369904 | D7: Servidor Web - Hosting | E7: ='Servidores Web - Hosting'!C8 -> 90000 | J7: Comunicación constante entre el equipo y el cliente
A8: Equipo Desarrolladores | B8: ='Equipo Desarrolladores'!I4 -> 2150000 | D8: Equipo Desarrolladores | E8: ='Equipo Desarrolladores'!I4 -> 2150000 | I8: Sprint Retrospective: Sesión interna del equipo para identificar mejoras en el proceso antes del siguiente sprint
A9: Equipos Consultorio | B9: ='Equipos Consultorio'!K4 -> 4300000 | D9: Equipos Consultorio | E9: ='Equipos Consultorio'!K4 -> 4300000 | J9: Mayor calidad del producto final gracias a revisiones continuas
A10: Total Estimado del Proyecto: | B10: =SUM(B3:B9) -> 56912345 | D10: Total Estimado del Proyecto: | E10: =SUM(E3:E9) -> 48632441
A12: Tiempo de Desarrollo | B12: 21 meses | D12: Tiempo de Desarrollo | E12: 21 meses
